approve_api_swagger/__init__.py
approve_api_swagger/api_client.py
approve_api_swagger/configuration.py
approve_api_swagger/rest.py
approve_api_swagger/api/__init__.py
approve_api_swagger/api/approve_api.py
approve_api_swagger/models/__init__.py
approve_api_swagger/models/error.py
approve_api_swagger/models/prompt.py
approve_api_swagger/models/prompt_answer.py
approve_api_swagger/models/prompt_status.py
test/__init__.py
test/test_approve_api.py
test/test_error.py
test/test_prompt.py
test/test_prompt_answer.py
test/test_prompt_status.py
approve_api_swagger-1.0.0.dist-info/METADATA
approve_api_swagger-1.0.0.dist-info/WHEEL
approve_api_swagger-1.0.0.dist-info/top_level.txt
approve_api_swagger-1.0.0.dist-info/RECORD
